README.md
bjson.py
setup.py
bjson.egg-info/PKG-INFO
bjson.egg-info/SOURCES.txt
bjson.egg-info/dependency_links.txt
bjson.egg-info/top_level.txt