Metadata-Version: 1.0
Name: bjson
Version: 0.2.1
Summary: Alternative way to send Python3 object by binary.
Home-page: https://github.com/namuyan/bin-json
Author: namuyan
Author-email: thhjuu@yahoo.co.jp
License: MIT
Platform: UNKNOWN
